qti2txt/__init__.py
qti2txt/backtoqti.py
qti2txt/builders.py
qti2txt/config_logging.py
qti2txt/config_questions.py
qti2txt/err.py
qti2txt/helpers.py
qti2txt/parsers.py
qti2txt/processors.py
qti2txt/qti2txt.py
qti2txt-0.0.1.dist-info/licenses/LICENSE
qti2txt-0.0.1.dist-info/WHEEL
qti2txt-0.0.1.dist-info/entry_points.txt
qti2txt-0.0.1.dist-info/METADATA
qti2txt-0.0.1.dist-info/RECORD
