Metadata-Version: 2.4
Name: qti2txt
Version: 0.0.1
Summary: Used to turn CANVAS QTI quizzes into plaintext files. Useful if you want more control over your quizzes or if you want to edit them and reupload them using text2qti.
Keywords: qti,canvas,quiz,conversion,lms,education
Author: davidagler
Author-email: davidagler <davidagler@users.noreply.github.com>
License-Expression: AGPL-3.0-or-later
License-File: LICENSE
Requires-Dist: defusedxml>=0.7.1
Requires-Dist: html2text>=2025.4.15
Requires-Python: >=3.13
Project-URL: Changelog, https://github.com/davidagler/qti2txt/blob/main/CHANGELOG.md
Project-URL: Homepage, https://github.com/davidagler/qti2txt
Project-URL: Repository, https://github.com/davidagler/qti2txt
